kivy_garden/i18n/__init__.py
kivy_garden/i18n/fontfinder.py
kivy_garden/i18n/localizer.py
kivy_garden/i18n/utils/__init__.py
kivy_garden/i18n/utils/_extract_msgids_from_string_literals.py
kivy_garden_i18n-0.3.0.dist-info/WHEEL
kivy_garden_i18n-0.3.0.dist-info/entry_points.txt
kivy_garden_i18n-0.3.0.dist-info/METADATA
kivy_garden_i18n-0.3.0.dist-info/RECORD
