Metadata-Version: 2.4
Name: kivy-garden-i18n
Version: 0.3.0
Summary: i18n for Kivy
Keywords: kivy
Author: Nattōsai Mitō
Author-email: Nattōsai Mitō <flow4re2c@gmail.com>
License-Expression: MIT
Classifier: Development Status :: 4 - Beta
Classifier: License :: OSI Approved :: MIT License
Classifier: Intended Audience :: Developers
Classifier: Programming Language :: Python
Classifier: Programming Language :: Python :: 3.10
Classifier: Programming Language :: Python :: 3.11
Classifier: Programming Language :: Python :: 3.12
Classifier: Programming Language :: Python :: 3.13
Classifier: Programming Language :: Python :: 3.14
Classifier: Topic :: Software Development :: Libraries
Classifier: Operating System :: OS Independent
Requires-Python: >=3.10, <4.0
Project-URL: Repository, https://github.com/gottadiveintopython/i18n
Project-URL: Documentation, https://gottadiveintopython.github.io/i18n/
